torch_crps/__init__.py
torch_crps/analytical_crps.py
torch_crps/ensemble_crps.py
torch_crps/integral_crps.py
torch_crps/utils.py
torch_crps-0.1.6.dist-info/METADATA
torch_crps-0.1.6.dist-info/WHEEL
torch_crps-0.1.6.dist-info/RECORD
