Metadata-Version: 2.4
Name: torch-crps
Version: 0.1.6
Summary: Implementations of the CRPS using PyTorch
Project-URL: homepage, https://famura.github.io/torch-crps
Project-URL: source, https://github.com/famura/torch-crps
Author-email: Fabio Muratore <accounts@famura.net>
Maintainer-email: Fabio Muratore <accounts@famura.net>
License-Expression: CC-BY-4.0
Classifier: Development Status :: 3 - Alpha
Classifier: Intended Audience :: Science/Research
Classifier: Natural Language :: English
Classifier: Programming Language :: Python :: 3.11
Classifier: Programming Language :: Python :: 3.12
Classifier: Programming Language :: Python :: 3.13
Classifier: Topic :: Scientific/Engineering
Requires-Python: >=3.11
Requires-Dist: torch>=2.7
